__init__.py
backend.py
display.py
weather_display-0.0.1.dist-info/licenses/LICENSE
weather_display-0.0.1.dist-info/METADATA
weather_display-0.0.1.dist-info/WHEEL
weather_display-0.0.1.dist-info/top_level.txt
weather_display-0.0.1.dist-info/RECORD
