Metadata-Version: 2.4
Name: weather-display
Version: 0.0.1
Summary: A TUI Weather Display.
Author-email: Wyatt Johnson <enderprooffical@gmail.com>
License: MIT
Requires-Python: >=3.8
License-File: LICENSE
Dynamic: license-file
